dlt_meta-0.0.10.dist-info/licenses/LICENSE.txt
integration_tests/__init__.py
integration_tests/cleanup_script.py
integration_tests/run_integration_tests.py
src/__about__.py
src/__init__.py
src/__main__.py
src/cli.py
src/config.py
src/dataflow_pipeline.py
src/dataflow_spec.py
src/install.py
src/metastore_ops.py
src/onboard_dataflowspec.py
src/pipeline_readers.py
src/pipeline_writers.py
src/uninstall.py
dlt_meta-0.0.10.dist-info/METADATA
dlt_meta-0.0.10.dist-info/WHEEL
dlt_meta-0.0.10.dist-info/entry_points.txt
dlt_meta-0.0.10.dist-info/top_level.txt
dlt_meta-0.0.10.dist-info/RECORD
