Metadata-Version: 2.4
Name: dlt_meta
Version: 0.0.10
Summary: DLT-META Framework
Author: Ravi Gawai
Author-email: databrickslabs@databricks.com
License: Databricks License
Classifier: Programming Language :: Python :: 3
Classifier: Operating System :: OS Independent
Classifier: Topic :: Software Development :: Testing
Classifier: Intended Audience :: Developers
Classifier: Intended Audience :: System Administrators
Requires-Python: >=3.8
License-File: LICENSE.txt
Requires-Dist: setuptools
Requires-Dist: databricks-sdk
Requires-Dist: PyYAML>=6.0
Provides-Extra: dev
Requires-Dist: flake8==6.0; extra == "dev"
Requires-Dist: delta-spark==3.0.0; extra == "dev"
Requires-Dist: pytest>=7.0.0; extra == "dev"
Requires-Dist: coverage>=7.0.0; extra == "dev"
Requires-Dist: pyspark==3.5.5; extra == "dev"
Provides-Extra: it
Requires-Dist: typer[all]==0.6.1; extra == "it"
Dynamic: author
Dynamic: author-email
Dynamic: classifier
Dynamic: description
Dynamic: description-content-type
Dynamic: license
Dynamic: license-file
Dynamic: provides-extra
Dynamic: requires-dist
Dynamic: requires-python
Dynamic: summary
